LICENSE
MANIFEST.in
README.md
requirements.txt
setup.cfg
setup.py
callback/__init__.py
callback/admin.py
callback/forms.py
callback/models.py
callback/urls.py
callback/views.py
callback/migrations/0001_initial.py
callback/migrations/0002_auto_20220112_1433.py
callback/migrations/__init__.py
callback/static/modal.js
callback/templates/modal.html
callback/templates/callback/add_callback.html
callback/templates/callback/callback_list.html
django_bm_callback.egg-info/PKG-INFO
django_bm_callback.egg-info/SOURCES.txt
django_bm_callback.egg-info/dependency_links.txt
django_bm_callback.egg-info/top_level.txt