Metadata-Version: 1.1
Name: django-bm-callback
Version: 0.0.1
Summary: Django callback app
Home-page: https://github.com/MykolaBerkosha/bm-callback
Author: Mykola Berkosha
Author-email: mberkosa@gmail.com
License: MIT
Download-URL: https://github.com/MykolaBerkosha/bm-callback/archive/0.0.1.tar.gz
Platform: UNKNOWN
